yaml_serde/__init__.py
yaml_serde-0.4.4.dist-info/LICENSE
yaml_serde-0.4.4.dist-info/METADATA
yaml_serde-0.4.4.dist-info/WHEEL
yaml_serde-0.4.4.dist-info/top_level.txt
yaml_serde-0.4.4.dist-info/RECORD
