Metadata-Version: 2.1
Name: yaml-serde
Version: 0.4.4
Summary: Python library for simplified YAML object serialization
Home-page: https://github.com/mentalsmash/yaml-serde
Author: mentalsmash.org
Author-email: support@mentalsmash.org
License: License :: OSI Approved :: Apache Software License
Platform: UNKNOWN
Classifier: Development Status :: 3 - Alpha
Classifier: Programming Language :: Python :: 3
Classifier: License :: OSI Approved :: Apache Software License
Requires-Python: >=3.6, <4
Requires-Dist: pyyaml (>=5.1)
